phone_number_validator_eusojk/__init__.py
phone_number_validator_eusojk/validator.py
phone_number_validator_eusojk-0.1.0.dist-info/METADATA
phone_number_validator_eusojk-0.1.0.dist-info/WHEEL
phone_number_validator_eusojk-0.1.0.dist-info/RECORD
