Metadata-Version: 2.1
Name: phone-number-validator-eusojk
Version: 0.1.0
Summary: 
Author: Josué
Author-email: josue.kpodo@gmail.com
Requires-Python: >=3.11,<4.0
Classifier: Programming Language :: Python :: 3
Classifier: Programming Language :: Python :: 3.11
Classifier: Programming Language :: Python :: 3.12
Classifier: Programming Language :: Python :: 3.13
Requires-Dist: requests (>=2.32.3,<3.0.0)
